emoji_data_python/__init__.py
emoji_data_python/conversion.py
emoji_data_python/emoji_char.py
emoji_data_python/replacement.py
emoji_data_python/search.py
emoji_data_python/data/emoji.json
tests/__init__.py
tests/test_conversion.py
tests/test_emoji_char.py
tests/test_replacement.py
tests/test_search.py
emoji_data_python-1.6.0.dist-info/LICENSE
emoji_data_python-1.6.0.dist-info/METADATA
emoji_data_python-1.6.0.dist-info/WHEEL
emoji_data_python-1.6.0.dist-info/top_level.txt
emoji_data_python-1.6.0.dist-info/RECORD
